setup.py
vectionary/__init__.py
vectionary/test_vectionary.py
vectionary.egg-info/PKG-INFO
vectionary.egg-info/SOURCES.txt
vectionary.egg-info/dependency_links.txt
vectionary.egg-info/entry_points.txt
vectionary.egg-info/not-zip-safe
vectionary.egg-info/top_level.txt