Metadata-Version: 1.1
Name: vectionary
Version: 0.1.0
Summary: add vector method to dict and Counter
Home-page: https://github.com/kitsuyui/vectionary
Author: kitsu yui
Author-email: yui.kitsu+git@gmail.com
License: 
